torch_waymo/__init__.py
torch_waymo/convert_waymo.py
torch_waymo/show_waymo.py
torch_waymo/dataset/__init__.py
torch_waymo/dataset/simplified_frame.py
torch_waymo/dataset/waymo_dataset.py
torch_waymo/protocol/__init__.py
torch_waymo/protocol/dataset_proto.py
torch_waymo/protocol/keypoint_proto.py
torch_waymo/protocol/label_proto.py
torch_waymo/protocol/utils.py
torch_waymo-0.1.5.dist-info/licenses/LICENSE
torch_waymo-0.1.5.dist-info/METADATA
torch_waymo-0.1.5.dist-info/WHEEL
torch_waymo-0.1.5.dist-info/entry_points.txt
torch_waymo-0.1.5.dist-info/top_level.txt
torch_waymo-0.1.5.dist-info/RECORD
