Metadata-Version: 2.4
Name: torch_waymo
Version: 0.1.5
Summary: Load Waymo Open Dataset in PyTorch
Author-email: William Guimont-Martin <william.guimont-martin@norlab.ulaval.ca>
Project-URL: Homepage, https://github.com/willGuimont/torch_waymo
Project-URL: Bug Tracker, https://github.com/willGuimont/torch_waymo/issues
Classifier: Programming Language :: Python :: 3
Classifier: License :: OSI Approved :: MIT License
Classifier: Operating System :: OS Independent
Requires-Python: >=3.7
License-File: LICENSE
Requires-Dist: tqdm
Requires-Dist: torch
Requires-Dist: numpy
Provides-Extra: waymo
Requires-Dist: waymo-open-dataset-tf-2-11-0; extra == "waymo"
Requires-Dist: protobuf; extra == "waymo"
Requires-Dist: tensorflow[and-cuda]; extra == "waymo"
Requires-Dist: numpy<2; extra == "waymo"
Dynamic: license-file
